repo2env/__init__.py
repo2env/__main__.py
repo2env/environment.py
repo2env/fetch.py
repo2env/git_util.py
repo2env-0.1.2.dist-info/LICENSE
repo2env-0.1.2.dist-info/METADATA
repo2env-0.1.2.dist-info/WHEEL
repo2env-0.1.2.dist-info/entry_points.txt
repo2env-0.1.2.dist-info/top_level.txt
repo2env-0.1.2.dist-info/RECORD
