Metadata-Version: 2.1
Name: repo2env
Version: 0.1.2
Summary: Automated environment parsing for AiiDAlab apps.
Home-page: https://github.com/aiidalab/repo2env
Author: Carl Simon Adorf
Author-email: simon.adorf@epfl.ch
License: MIT
Platform: UNKNOWN
Classifier: Development Status :: 4 - Beta
Classifier: Framework :: AiiDA
Classifier: License :: OSI Approved :: MIT License
Classifier: Programming Language :: Python :: 3.7
Classifier: Programming Language :: Python :: 3.8
Classifier: Programming Language :: Python :: 3.9
License-File: LICENSE
Requires-Dist: click (~=7.1)
Requires-Dist: dulwich (~=0.20.15)
Requires-Dist: requests (~=2.24)
Provides-Extra: dev
Requires-Dist: bump2version (==1.0.1) ; extra == 'dev'
Requires-Dist: pre-commit (==2.12.1) ; extra == 'dev'
